calculadoradesarrollo/Calculadoradesarrollo.py
calculadoradesarrollo/__init__.py
calculadora_desarrollo_kevin-0.1.0.dist-info/METADATA
calculadora_desarrollo_kevin-0.1.0.dist-info/WHEEL
calculadora_desarrollo_kevin-0.1.0.dist-info/entry_points.txt
calculadora_desarrollo_kevin-0.1.0.dist-info/top_level.txt
calculadora_desarrollo_kevin-0.1.0.dist-info/RECORD
