Metadata-Version: 2.4
Name: calculadora-desarrollo-kevin
Version: 0.1.0
Summary: Calculadora básica en Python con estados
Author-email: Kevin Cruz <kacruzv@udistrital.edu.co>
License: MIT
Requires-Python: >=3.8
